{"Abu Dhabi":[{"date":"2026-02-24","mean_radiance":28.107,"pct_change":10.6,"cloud_fraction":0.73,"source":"VNP46A2"},{"date":"2026-02-26","mean_radiance":34.867,"pct_change":17.1,"cloud_fraction":0.6,"source":"VNP46A2"},{"date":"2026-02-27","mean_radiance":23.768,"pct_change":-10.9,"cloud_fraction":0.0,"source":"VIIRS_DNB_L1B"},{"date":"2026-02-28","mean_radiance":25.235,"pct_change":-4.6,"cloud_fraction":0.0,"source":"VIIRS_DNB_L1B"},{"date":"2026-03-01","mean_radiance":24.49,"pct_change":-7.4,"cloud_fraction":0.0,"source":"VIIRS_DNB_L1B"},{"date":"2026-03-02","mean_radiance":25.752,"pct_change":-2.6,"cloud_fraction":0.0,"source":"VIIRS_DNB_L1B"},{"date":"2026-03-03","mean_radiance":27.998,"pct_change":5.9,"cloud_fraction":0.0,"source":"VIIRS_DNB_L1B"},{"date":"2026-03-04","mean_radiance":25.951,"pct_change":-1.9,"cloud_fraction":0.0,"source":"VIIRS_DNB_L1B"},{"date":"2026-03-05","mean_radiance":23.549,"pct_change":-10.9,"cloud_fraction":0.0,"source":"VIIRS_DNB_L1B"},{"date":"2026-03-06","mean_radiance":24.638,"pct_change":-6.8,"cloud_fraction":0.0,"source":"VIIRS_DNB_L1B"},{"date":"2026-03-07","mean_radiance":15.5,"pct_change":-41.4,"cloud_fraction":0.0,"source":"VIIRS_DNB_L1B"},{"date":"2026-03-08","mean_radiance":10.557,"pct_change":-60.1,"cloud_fraction":0.0,"source":"VIIRS_DNB_L1B"}],"Auckland":[{"date":"2026-01-24","mean_radiance":4.544,"pct_change":52.8,"cloud_fraction":1.0,"source":"VNP46A2"},{"date":"2026-01-27","mean_radiance":3.016,"pct_change":1.4,"cloud_fraction":1.0,"source":"VNP46A2"},{"date":"2026-01-30","mean_radiance":2.765,"pct_change":-7.0,"cloud_fraction":1.0,"source":"VNP46A2"},{"date":"2026-02-02","mean_radiance":8.896,"pct_change":199.1,"cloud_fraction":1.0,"source":"VNP46A2"},{"date":"2026-02-05","mean_radiance":3.093,"pct_change":4.0,"cloud_fraction":1.0,"source":"VNP46A2"},{"date":"2026-02-08","mean_radiance":3.881,"pct_change":30.5,"cloud_fraction":1.0,"source":"VNP46A2"},{"date":"2026-02-11","mean_radiance":2.422,"pct_change":-18.6,"cloud_fraction":1.0,"source":"VNP46A2"},{"date":"2026-02-14","mean_radiance":1.772,"pct_change":-40.4,"cloud_fraction":1.0,"source":"VNP46A2"},{"date":"2026-02-17","mean_radiance":1.431,"pct_change":-51.9,"cloud_fraction":1.0,"source":"VNP46A2"},{"date":"2026-02-20","mean_radiance":1.746,"pct_change":-41.3,"cloud_fraction":1.0,"source":"VNP46A2"},{"date":"2026-02-23","mean_radiance":2.542,"pct_change":-14.6,"cloud_fraction":1.0,"source":"VNP46A2"},{"date":"2026-02-26","mean_radiance":2.74,"pct_change":-7.9,"cloud_fraction":1.0,"source":"VNP46A2"}],"Basra":[{"date":"2026-02-24","mean_radiance":41.618,"pct_change":5.2,"cloud_fraction":0.2,"source":"VNP46A2"},{"date":"2026-02-26","mean_radiance":37.587,"pct_change":0.3,"cloud_fraction":0.27,"source":"VNP46A2"},{"date":"2026-02-27","mean_radiance":59.702,"pct_change":59.3,"cloud_fraction":0.0,"source":"VIIRS_DNB_L1B"},{"date":"2026-02-28","mean_radiance":55.578,"pct_change":41.3,"cloud_fraction":0.0,"source":"VIIRS_DNB_L1B"},{"date":"2026-03-01","mean_radiance":54.115,"pct_change":37.6,"cloud_fraction":0.0,"source":"VIIRS_DNB_L1B"},{"date":"2026-03-02","mean_radiance":58.407,"pct_change":48.5,"cloud_fraction":0.0,"source":"VIIRS_DNB_L1B"},{"date":"2026-03-03","mean_radiance":54.801,"pct_change":39.3,"cloud_fraction":0.0,"source":"VIIRS_DNB_L1B"},{"date":"2026-03-04","mean_radiance":31.903,"pct_change":-18.9,"cloud_fraction":0.0,"source":"VIIRS_DNB_L1B"},{"date":"2026-03-05","mean_radiance":53.955,"pct_change":37.2,"cloud_fraction":0.0,"source":"VIIRS_DNB_L1B"},{"date":"2026-03-06","mean_radiance":49.061,"pct_change":24.7,"cloud_fraction":0.0,"source":"VIIRS_DNB_L1B"},{"date":"2026-03-07","mean_radiance":17.56,"pct_change":-55.4,"cloud_fraction":0.0,"source":"VIIRS_DNB_L1B"},{"date":"2026-03-08","mean_radiance":51.611,"pct_change":31.2,"cloud_fraction":0.0,"source":"VIIRS_DNB_L1B"}],"Doha":[{"date":"2026-02-24","mean_radiance":81.057,"pct_change":6.3,"cloud_fraction":0.49,"source":"VNP46A2"},{"date":"2026-02-26","mean_radiance":87.639,"pct_change":15.3,"cloud_fraction":0.53,"source":"VNP46A2"},{"date":"2026-02-27","mean_radiance":91.827,"pct_change":20.0,"cloud_fraction":0.0,"source":"VIIRS_DNB_L1B"},{"date":"2026-02-28","mean_radiance":99.492,"pct_change":27.9,"cloud_fraction":0.0,"source":"VIIRS_DNB_L1B"},{"date":"2026-03-01","mean_radiance":100.735,"pct_change":29.5,"cloud_fraction":0.0,"source":"VIIRS_DNB_L1B"},{"date":"2026-03-02","mean_radiance":76.128,"pct_change":-2.1,"cloud_fraction":0.0,"source":"VIIRS_DNB_L1B"},{"date":"2026-03-03","mean_radiance":61.787,"pct_change":-20.6,"cloud_fraction":0.0,"source":"VIIRS_DNB_L1B"},{"date":"2026-03-04","mean_radiance":98.07,"pct_change":26.1,"cloud_fraction":0.0,"source":"VIIRS_DNB_L1B"},{"date":"2026-03-05","mean_radiance":91.367,"pct_change":17.5,"cloud_fraction":0.0,"source":"VIIRS_DNB_L1B"},{"date":"2026-03-06","mean_radiance":102.512,"pct_change":31.8,"cloud_fraction":0.0,"source":"VIIRS_DNB_L1B"},{"date":"2026-03-07","mean_radiance":96.115,"pct_change":23.6,"cloud_fraction":0.0,"source":"VIIRS_DNB_L1B"},{"date":"2026-03-08","mean_radiance":82.849,"pct_change":6.5,"cloud_fraction":0.0,"source":"VIIRS_DNB_L1B"}],"Dubai":[{"date":"2026-02-24","mean_radiance":67.78,"pct_change":45.0,"cloud_fraction":0.48,"source":"VNP46A2"},{"date":"2026-02-26","mean_radiance":55.8,"pct_change":-3.0,"cloud_fraction":0.5,"source":"VNP46A2"},{"date":"2026-02-27","mean_radiance":43.186,"pct_change":-16.5,"cloud_fraction":0.0,"source":"VIIRS_DNB_L1B"},{"date":"2026-02-28","mean_radiance":44.32,"pct_change":-13.2,"cloud_fraction":0.0,"source":"VIIRS_DNB_L1B"},{"date":"2026-03-01","mean_radiance":45.21,"pct_change":-11.4,"cloud_fraction":0.01,"source":"VIIRS_DNB_L1B"},{"date":"2026-03-02","mean_radiance":42.593,"pct_change":-16.5,"cloud_fraction":0.0,"source":"VIIRS_DNB_L1B"},{"date":"2026-03-03","mean_radiance":47.187,"pct_change":-7.5,"cloud_fraction":0.0,"source":"VIIRS_DNB_L1B"},{"date":"2026-03-04","mean_radiance":41.25,"pct_change":-19.2,"cloud_fraction":0.0,"source":"VIIRS_DNB_L1B"},{"date":"2026-03-05","mean_radiance":43.222,"pct_change":-15.3,"cloud_fraction":0.0,"source":"VIIRS_DNB_L1B"},{"date":"2026-03-06","mean_radiance":37.78,"pct_change":-26.0,"cloud_fraction":0.0,"source":"VIIRS_DNB_L1B"},{"date":"2026-03-07","mean_radiance":20.225,"pct_change":-60.4,"cloud_fraction":0.0,"source":"VIIRS_DNB_L1B"},{"date":"2026-03-08","mean_radiance":31.701,"pct_change":-37.9,"cloud_fraction":0.0,"source":"VIIRS_DNB_L1B"}],"Isfahan":[{"date":"2026-02-24","mean_radiance":19.331,"pct_change":93.6,"cloud_fraction":0.74,"source":"VNP46A2"},{"date":"2026-02-26","mean_radiance":13.265,"pct_change":74.3,"cloud_fraction":0.69,"source":"VNP46A2"},{"date":"2026-02-27","mean_radiance":18.48,"pct_change":59.2,"cloud_fraction":0.0,"source":"VIIRS_DNB_L1B"},{"date":"2026-02-28","mean_radiance":21.617,"pct_change":77.5,"cloud_fraction":0.0,"source":"VIIRS_DNB_L1B"},{"date":"2026-03-01","mean_radiance":17.806,"pct_change":46.2,"cloud_fraction":0.0,"source":"VIIRS_DNB_L1B"},{"date":"2026-03-02","mean_radiance":20.102,"pct_change":65.0,"cloud_fraction":0.0,"source":"VIIRS_DNB_L1B"},{"date":"2026-03-03","mean_radiance":20.428,"pct_change":67.7,"cloud_fraction":0.0,"source":"VIIRS_DNB_L1B"},{"date":"2026-03-04","mean_radiance":19.197,"pct_change":57.6,"cloud_fraction":0.0,"source":"VIIRS_DNB_L1B"},{"date":"2026-03-05","mean_radiance":20.991,"pct_change":72.3,"cloud_fraction":0.0,"source":"VIIRS_DNB_L1B"},{"date":"2026-03-06","mean_radiance":13.938,"pct_change":14.4,"cloud_fraction":0.0,"source":"VIIRS_DNB_L1B"},{"date":"2026-03-07","mean_radiance":12.461,"pct_change":2.3,"cloud_fraction":0.0,"source":"VIIRS_DNB_L1B"},{"date":"2026-03-08","mean_radiance":10.979,"pct_change":-9.9,"cloud_fraction":0.0,"source":"VIIRS_DNB_L1B"}],"Kuwait City":[{"date":"2026-02-24","mean_radiance":37.672,"pct_change":5.1,"cloud_fraction":0.61,"source":"VNP46A2"},{"date":"2026-02-26","mean_radiance":41.578,"pct_change":11.1,"cloud_fraction":0.59,"source":"VNP46A2"},{"date":"2026-02-27","mean_radiance":46.681,"pct_change":24.2,"cloud_fraction":0.0,"source":"VIIRS_DNB_L1B"},{"date":"2026-02-28","mean_radiance":40.758,"pct_change":6.3,"cloud_fraction":0.0,"source":"VIIRS_DNB_L1B"},{"date":"2026-03-01","mean_radiance":42.512,"pct_change":10.9,"cloud_fraction":0.0,"source":"VIIRS_DNB_L1B"},{"date":"2026-03-02","mean_radiance":42.365,"pct_change":10.5,"cloud_fraction":0.0,"source":"VIIRS_DNB_L1B"},{"date":"2026-03-03","mean_radiance":37.606,"pct_change":-1.9,"cloud_fraction":0.0,"source":"VIIRS_DNB_L1B"},{"date":"2026-03-04","mean_radiance":42.399,"pct_change":10.6,"cloud_fraction":0.0,"source":"VIIRS_DNB_L1B"},{"date":"2026-03-05","mean_radiance":33.496,"pct_change":-12.6,"cloud_fraction":0.0,"source":"VIIRS_DNB_L1B"},{"date":"2026-03-06","mean_radiance":32.345,"pct_change":-15.6,"cloud_fraction":0.0,"source":"VIIRS_DNB_L1B"},{"date":"2026-03-07","mean_radiance":23.81,"pct_change":-37.9,"cloud_fraction":0.0,"source":"VIIRS_DNB_L1B"},{"date":"2026-03-08","mean_radiance":31.358,"pct_change":-18.2,"cloud_fraction":0.0,"source":"VIIRS_DNB_L1B"}],"Manama":[{"date":"2026-02-24","mean_radiance":25.524,"pct_change":-23.8,"cloud_fraction":0.9,"source":"VNP46A2"},{"date":"2026-02-26","mean_radiance":25.609,"pct_change":-53.1,"cloud_fraction":0.9,"source":"VNP46A2"},{"date":"2026-02-27","mean_radiance":48.039,"pct_change":57.0,"cloud_fraction":0.0,"source":"VIIRS_DNB_L1B"},{"date":"2026-02-28","mean_radiance":48.779,"pct_change":52.2,"cloud_fraction":0.0,"source":"VIIRS_DNB_L1B"},{"date":"2026-03-01","mean_radiance":51.64,"pct_change":61.1,"cloud_fraction":0.0,"source":"VIIRS_DNB_L1B"},{"date":"2026-03-02","mean_radiance":44.295,"pct_change":38.2,"cloud_fraction":0.0,"source":"VIIRS_DNB_L1B"},{"date":"2026-03-03","mean_radiance":40.733,"pct_change":27.1,"cloud_fraction":0.0,"source":"VIIRS_DNB_L1B"},{"date":"2026-03-04","mean_radiance":36.909,"pct_change":15.1,"cloud_fraction":0.0,"source":"VIIRS_DNB_L1B"},{"date":"2026-03-05","mean_radiance":23.056,"pct_change":-28.1,"cloud_fraction":0.0,"source":"VIIRS_DNB_L1B"},{"date":"2026-03-06","mean_radiance":49.465,"pct_change":54.3,"cloud_fraction":0.0,"source":"VIIRS_DNB_L1B"},{"date":"2026-03-07","mean_radiance":35.45,"pct_change":10.6,"cloud_fraction":0.0,"source":"VIIRS_DNB_L1B"},{"date":"2026-03-08","mean_radiance":47.819,"pct_change":49.2,"cloud_fraction":0.0,"source":"VIIRS_DNB_L1B"}],"Queenstown":[{"date":"2026-01-24","mean_radiance":0.591,"pct_change":-4.6,"cloud_fraction":1.0,"source":"VNP46A2"},{"date":"2026-01-27","mean_radiance":0.213,"pct_change":-65.7,"cloud_fraction":0.98,"source":"VNP46A2"},{"date":"2026-01-30","mean_radiance":0.427,"pct_change":-31.2,"cloud_fraction":0.98,"source":"VNP46A2"},{"date":"2026-02-02","mean_radiance":1.655,"pct_change":167.0,"cloud_fraction":1.0,"source":"VNP46A2"},{"date":"2026-02-05","mean_radiance":0.097,"pct_change":-84.4,"cloud_fraction":0.98,"source":"VNP46A2"},{"date":"2026-02-08","mean_radiance":3.472,"pct_change":460.1,"cloud_fraction":1.0,"source":"VNP46A2"},{"date":"2026-02-11","mean_radiance":0.355,"pct_change":-42.8,"cloud_fraction":0.99,"source":"VNP46A2"},{"date":"2026-02-14","mean_radiance":0.398,"pct_change":-35.9,"cloud_fraction":0.99,"source":"VNP46A2"},{"date":"2026-02-17","mean_radiance":0.235,"pct_change":-62.0,"cloud_fraction":1.0,"source":"VNP46A2"},{"date":"2026-02-20","mean_radiance":0.3,"pct_change":-51.5,"cloud_fraction":1.0,"source":"VNP46A2"},{"date":"2026-02-23","mean_radiance":0.279,"pct_change":-55.0,"cloud_fraction":0.98,"source":"VNP46A2"},{"date":"2026-02-26","mean_radiance":0.399,"pct_change":-35.6,"cloud_fraction":1.0,"source":"VNP46A2"}],"Riyadh":[{"date":"2026-02-24","mean_radiance":120.945,"pct_change":27.6,"cloud_fraction":0.27,"source":"VNP46A2"},{"date":"2026-02-26","mean_radiance":127.466,"pct_change":21.7,"cloud_fraction":0.27,"source":"VNP46A2"},{"date":"2026-02-27","mean_radiance":56.795,"pct_change":-47.5,"cloud_fraction":0.0,"source":"VIIRS_DNB_L1B"},{"date":"2026-02-28","mean_radiance":54.742,"pct_change":-47.3,"cloud_fraction":0.0,"source":"VIIRS_DNB_L1B"},{"date":"2026-03-01","mean_radiance":59.186,"pct_change":-43.1,"cloud_fraction":0.0,"source":"VIIRS_DNB_L1B"},{"date":"2026-03-02","mean_radiance":65.247,"pct_change":-37.2,"cloud_fraction":0.0,"source":"VIIRS_DNB_L1B"},{"date":"2026-03-03","mean_radiance":58.451,"pct_change":-43.8,"cloud_fraction":0.0,"source":"VIIRS_DNB_L1B"},{"date":"2026-03-04","mean_radiance":63.27,"pct_change":-39.1,"cloud_fraction":0.0,"source":"VIIRS_DNB_L1B"},{"date":"2026-03-05","mean_radiance":57.397,"pct_change":-44.8,"cloud_fraction":0.0,"source":"VIIRS_DNB_L1B"},{"date":"2026-03-06","mean_radiance":55.785,"pct_change":-46.3,"cloud_fraction":0.0,"source":"VIIRS_DNB_L1B"},{"date":"2026-03-07","mean_radiance":33.841,"pct_change":-67.4,"cloud_fraction":0.0,"source":"VIIRS_DNB_L1B"},{"date":"2026-03-08","mean_radiance":56.023,"pct_change":-46.1,"cloud_fraction":0.0,"source":"VIIRS_DNB_L1B"}],"Tehran":[{"date":"2026-02-24","mean_radiance":29.329,"pct_change":36.6,"cloud_fraction":0.98,"source":"VNP46A2"},{"date":"2026-02-27","mean_radiance":17.3,"pct_change":-23.3,"cloud_fraction":0.0,"source":"VIIRS_DNB_L1B"},{"date":"2026-02-28","mean_radiance":18.697,"pct_change":-17.1,"cloud_fraction":0.02,"source":"VIIRS_DNB_L1B"},{"date":"2026-03-01","mean_radiance":17.576,"pct_change":-22.1,"cloud_fraction":0.0,"source":"VIIRS_DNB_L1B"},{"date":"2026-03-02","mean_radiance":21.502,"pct_change":-4.7,"cloud_fraction":0.0,"source":"VIIRS_DNB_L1B"},{"date":"2026-03-03","mean_radiance":20.797,"pct_change":-7.8,"cloud_fraction":0.0,"source":"VIIRS_DNB_L1B"},{"date":"2026-03-04","mean_radiance":19.593,"pct_change":-13.2,"cloud_fraction":0.0,"source":"VIIRS_DNB_L1B"},{"date":"2026-03-05","mean_radiance":19.967,"pct_change":-11.5,"cloud_fraction":0.0,"source":"VIIRS_DNB_L1B"},{"date":"2026-03-06","mean_radiance":12.911,"pct_change":-42.8,"cloud_fraction":0.0,"source":"VIIRS_DNB_L1B"},{"date":"2026-03-07","mean_radiance":12.285,"pct_change":-45.6,"cloud_fraction":0.0,"source":"VIIRS_DNB_L1B"},{"date":"2026-03-08","mean_radiance":5.064,"pct_change":-77.6,"cloud_fraction":0.0,"source":"VIIRS_DNB_L1B"}]}